{"id": "EAExU-BUp0E-1-0-web-2-3PBXxowEzss", "caption": "The image features a Merry Christmas and Happy New Year greeting with a deer head on top. The deer head is surrounded by various Christmas decorations, including a star, a bow, and a few golden balls. The festive scene is set against a black background, which highlights the vibrant colors of the decorations. The overall atmosphere of the image is warm and celebratory, perfect for the holiday season.", "original_title": "Merry Christmas &amp; Happy New Year Instagram Story", "tags": ["black", "white", "yellow", "gold", "minimalist", "simple", "clean", "christmas", "vector", "decoration", "merry", "happy", "background", "holiday", "card", "new", "year", "design", "illustration", "winter"], "texts": ["merry", "christmas", "& happy ne year"], "category": "Your story", "text_layer_info": "[{\"text\": \"& happy ne year\\n\", \"position\": [937.4252946890964, 115.44737956939092, 42.52977415161133, 864.0000000000002], \"label\": \"subtitle\", \"style\": {\"text-transform\": \"uppercase\", \"color\": \"#ffffff\", \"font-weight\": \"medium\", \"font-size\": \"35.4335\", \"font-family\": \"YAFdtQi73Xs,0\", \"tracking\": \"311.0\", \"text-align\": \"center\", \"font-info\": {\"_id\": \"YAFdtQi73Xs\", \"fonts\": {\"style\": \"REGULAR\", \"styleName\": \"Regular\", \"postscriptName\": \"Montserrat-Regular\", \"weight\": 400, \"subsettedFiles\": [], \"metadata\": {\"head\": {\"unitsPerEm\": 1000, \"yMin\": -262, \"yMax\": 1043}, \"hhea\": {\"ascender\": 968, \"descender\": -251, \"lineGap\": 0}, \"os2\": {\"sTypoAscender\": 968, \"sTypoDescender\": -251, \"sTypoLineGap\": 0, \"usWinAscent\": 1109, \"usWinDescent\": 270, \"fsSelection\": 192}}, \"images\": [], \"replacedByRefs\": []}, \"index\": 0, \"files\": [{\"url\": \"https://font-public.canva.com/YAFdtQi73Xs/0/Montserrat-Regular.b1c97ca3ccb1538ad290d.b1c97ca3ccb1538ad290ddc7fb9e5999.ttf\", \"bucket\": \"font-public.canva.com\", \"key\": \"YAFdtQi73Xs/0/Montserrat-Regular.b1c97ca3ccb1538ad290d.b1c97ca3ccb1538ad290ddc7fb9e5999.ttf\", \"format\": \"OTF\", \"sizeBytes\": 263192}, {\"url\": \"https://font-public.canva.com/YAFdtQi73Xs/0/Montserrat-Regular.0a32c4953a7e6c3caf154.0a32c4953a7e6c3caf15493b72c6360c.woff\", \"bucket\": \"font-public.canva.com\", \"key\": \"YAFdtQi73Xs/0/Montserrat-Regular.0a32c4953a7e6c3caf154.0a32c4953a7e6c3caf15493b72c6360c.woff\", \"format\": \"WOFF\", \"sizeBytes\": 113984}, {\"url\": \"https://font-public.canva.com/YAFdtQi73Xs/0/Montserrat-Regular.b1c97ca3ccb1538ad290d.881b8da5ad9b82b143ab37dcdf069c4c.woff2\", \"bucket\": \"font-public.canva.com\", \"key\": \"YAFdtQi73Xs/0/Montserrat-Regular.b1c97ca3ccb1538ad290d.881b8da5ad9b82b143ab37dcdf069c4c.woff2\", \"format\": \"WOFF2\", \"sizeBytes\": 89932}]}, \"leading\": \"1400.0\"}, \"index\": 0}, {\"text\": \"christmas\\n\", \"position\": [844.9907904532564, 115.4473795693911, 92.43450423583984, 864.0000000000001], \"label\": \"title\", \"style\": {\"text-transform\": \"uppercase\", \"color\": \"#ffffff\", \"font-weight\": \"medium\", \"font-size\": \"77.032\", \"font-family\": \"YAFdtQi73Xs,0\", \"tracking\": \"311.0\", \"text-align\": \"center\", \"font-info\": {\"_id\": \"YAFdtQi73Xs\", \"fonts\": {\"style\": \"REGULAR\", \"styleName\": \"Regular\", \"postscriptName\": \"Montserrat-Regular\", \"weight\": 400, \"subsettedFiles\": [], \"metadata\": {\"head\": {\"unitsPerEm\": 1000, \"yMin\": -262, \"yMax\": 1043}, \"hhea\": {\"ascender\": 968, \"descender\": -251, \"lineGap\": 0}, \"os2\": {\"sTypoAscender\": 968, \"sTypoDescender\": -251, \"sTypoLineGap\": 0, \"usWinAscent\": 1109, \"usWinDescent\": 270, \"fsSelection\": 192}}, \"images\": [], \"replacedByRefs\": []}, \"index\": 0, \"files\": [{\"url\": \"https://font-public.canva.com/YAFdtQi73Xs/0/Montserrat-Regular.b1c97ca3ccb1538ad290d.b1c97ca3ccb1538ad290ddc7fb9e5999.ttf\", \"bucket\": \"font-public.canva.com\", \"key\": \"YAFdtQi73Xs/0/Montserrat-Regular.b1c97ca3ccb1538ad290d.b1c97ca3ccb1538ad290ddc7fb9e5999.ttf\", \"format\": \"OTF\", \"sizeBytes\": 263192}, {\"url\": \"https://font-public.canva.com/YAFdtQi73Xs/0/Montserrat-Regular.0a32c4953a7e6c3caf154.0a32c4953a7e6c3caf15493b72c6360c.woff\", \"bucket\": \"font-public.canva.com\", \"key\": \"YAFdtQi73Xs/0/Montserrat-Regular.0a32c4953a7e6c3caf154.0a32c4953a7e6c3caf15493b72c6360c.woff\", \"format\": \"WOFF\", \"sizeBytes\": 113984}, {\"url\": \"https://font-public.canva.com/YAFdtQi73Xs/0/Montserrat-Regular.b1c97ca3ccb1538ad290d.881b8da5ad9b82b143ab37dcdf069c4c.woff2\", \"bucket\": \"font-public.canva.com\", \"key\": \"YAFdtQi73Xs/0/Montserrat-Regular.b1c97ca3ccb1538ad290d.881b8da5ad9b82b143ab37dcdf069c4c.woff2\", \"format\": \"WOFF2\", \"sizeBytes\": 89932}]}, \"leading\": \"1400.0\"}, \"index\": 1}, {\"text\": \"merry\\n\", \"position\": [772.2677804532564, 115.44737956939105, 72.72301, 853.7990583624685], \"label\": \"pretitle\", \"style\": {\"text-transform\": \"uppercase\", \"color\": \"#ffffff\", \"font-weight\": \"medium\", \"font-size\": \"60.6037\", \"font-family\": \"YAFdtQi73Xs,0\", \"tracking\": \"311.0\", \"text-align\": \"center\", \"font-info\": {\"_id\": \"YAFdtQi73Xs\", \"fonts\": {\"style\": \"REGULAR\", \"styleName\": \"Regular\", \"postscriptName\": \"Montserrat-Regular\", \"weight\": 400, \"subsettedFiles\": [], \"metadata\": {\"head\": {\"unitsPerEm\": 1000, \"yMin\": -262, \"yMax\": 1043}, \"hhea\": {\"ascender\": 968, \"descender\": -251, \"lineGap\": 0}, \"os2\": {\"sTypoAscender\": 968, \"sTypoDescender\": -251, \"sTypoLineGap\": 0, \"usWinAscent\": 1109, \"usWinDescent\": 270, \"fsSelection\": 192}}, \"images\": [], \"replacedByRefs\": []}, \"index\": 0, \"files\": [{\"url\": \"https://font-public.canva.com/YAFdtQi73Xs/0/Montserrat-Regular.b1c97ca3ccb1538ad290d.b1c97ca3ccb1538ad290ddc7fb9e5999.ttf\", \"bucket\": \"font-public.canva.com\", \"key\": \"YAFdtQi73Xs/0/Montserrat-Regular.b1c97ca3ccb1538ad290d.b1c97ca3ccb1538ad290ddc7fb9e5999.ttf\", \"format\": \"OTF\", \"sizeBytes\": 263192}, {\"url\": \"https://font-public.canva.com/YAFdtQi73Xs/0/Montserrat-Regular.0a32c4953a7e6c3caf154.0a32c4953a7e6c3caf15493b72c6360c.woff\", \"bucket\": \"font-public.canva.com\", \"key\": \"YAFdtQi73Xs/0/Montserrat-Regular.0a32c4953a7e6c3caf154.0a32c4953a7e6c3caf15493b72c6360c.woff\", \"format\": \"WOFF\", \"sizeBytes\": 113984}, {\"url\": \"https://font-public.canva.com/YAFdtQi73Xs/0/Montserrat-Regular.b1c97ca3ccb1538ad290d.881b8da5ad9b82b143ab37dcdf069c4c.woff2\", \"bucket\": \"font-public.canva.com\", \"key\": \"YAFdtQi73Xs/0/Montserrat-Regular.b1c97ca3ccb1538ad290d.881b8da5ad9b82b143ab37dcdf069c4c.woff2\", \"format\": \"WOFF2\", \"sizeBytes\": 89932}]}, \"leading\": \"1400.0\"}, \"index\": 4}]"}