{"id": "EAE8X7p7Vfc-1-0-web-2-AB3YohYtmzE", "caption": "The image features a delicious chicken dish with black pepper sauce, presented in a black bowl. The chicken is crispy, sticky, saucy, and sweet, making it an ideal aspect of a wonderful chicken dish. The dish is part of a special menu, and the image is accompanied by a recipe that can be seen by clicking on the \"See the Recipe\" button. The image is titled \"Suhoor\" and is likely to be a part of a special menu.", "original_title": "Green Elegant Ramadhan Special Menu Instagram Story", "tags": ["Green", "Gold", "Elegant", "Illustration", "Modern", "Instagram Story", "Instagram Feed", "Ramadhan", "Mubarak", "Arabic", "Muslim", "Mosque", "Ramadan", "Ramadan Sale", "Ramadan Decoration", "Eid", "Kareem Eid Fitri", "Marhaban", "Quran", "Iftar"], "texts": ["Suhoor", "See the Recipe", "This black pepper chicken is crispy, sticky, saucy, and sweet, which are ideal aspects of a wonderful chicken dish.", "special menu", "chicken with black pepper sauce"], "category": "Your story", "text_layer_info": "[{\"text\": \"chicken with black pepper sauce\\n\", \"position\": [719.9987023022345, 326.92505834478357, 269.6137534359935, 441.3157630779306], \"label\": \"heading\", \"style\": {\"color\": \"#e4ccb6\", \"font-size\": \"33.3334\", \"font-family\": \"YAEe9XbWpNs,0\", \"tracking\": \"89.0\", \"text-align\": \"center\", \"font-info\": {\"_id\": \"YAEe9XbWpNs\", \"fonts\": {\"style\": \"REGULAR\", \"styleName\": \"Regular\", \"postscriptName\": \"CinzelDecorative-Regular\", \"weight\": 400, \"subsettedFiles\": [{\"type\": \"LOCALE_SUBSETTED_FONT_FILE\", \"url\": \"https://font-public.canva.com/YAEe9XbWpNs/0/subsets/CinzelDecorative-Regular.b41865e5f86a443.727c19e53000d2c4c27f062b210d0e47.ttf\", \"format\": \"OTF\", \"sizeBytes\": 50928, \"unicodeRanges\": [{\"start\": \"0000\", \"end\": \"007F\"}, {\"start\": \"0080\", \"end\": \"00FF\"}, {\"start\": \"0100\", \"end\": \"017F\"}, {\"start\": \"1E00\", \"end\": \"1EFF\"}], \"supportedLocales\": [\"en-AU\", \"en-instrume\", \"en-psaccent\", \"en\", \"en-GB\", \"en-IN\", \"jv-ID\", \"quc-GT\", \"rw-RW\", \"ms-MY\", \"om-ET\", \"en-PH\", \"sn-ZW\", \"en-OZ\", \"su-ID\", \"sw-KE\", \"uz-UZ\", \"xh-ZA\", \"zu-ZA\"]}, {\"type\": \"LOCALE_SUBSETTED_FONT_FILE\", \"url\": \"https://font-public.canva.com/YAEe9XbWpNs/0/subsets/CinzelDecorative-Regular.b41865e5f86a443.018333806f9baa45e457caeeffbce25.woff2\", \"format\": \"WOFF2\", \"sizeBytes\": 19616, \"unicodeRanges\": [{\"start\": \"0000\", \"end\": \"007F\"}, {\"start\": \"0080\", \"end\": \"00FF\"}, {\"start\": \"0100\", \"end\": \"017F\"}, {\"start\": \"1E00\", \"end\": \"1EFF\"}], \"supportedLocales\": [\"en-AU\", \"en-instrume\", \"en-psaccent\", \"en\", \"en-GB\", \"en-IN\", \"jv-ID\", \"quc-GT\", \"rw-RW\", \"ms-MY\", \"om-ET\", \"en-PH\", \"sn-ZW\", \"en-OZ\", \"su-ID\", \"sw-KE\", \"uz-UZ\", \"xh-ZA\", \"zu-ZA\"]}, {\"type\": \"LOCALE_SUBSETTED_FONT_FILE\", \"url\": \"https://font-public.canva.com/YAEe9XbWpNs/0/subsets/CinzelDecorative-Regular.b41865e5f86a443.98e3da708d9186b7ea1e9110280ab1c4.woff\", \"format\": \"WOFF\", \"sizeBytes\": 21556, \"unicodeRanges\": [{\"start\": \"0000\", \"end\": \"007F\"}, {\"start\": \"0080\", \"end\": \"00FF\"}, {\"start\": \"0100\", \"end\": \"017F\"}, {\"start\": \"1E00\", \"end\": \"1EFF\"}], \"supportedLocales\": [\"en-AU\", \"en-instrume\", \"en-psaccent\", \"en\", \"en-GB\", \"en-IN\", \"jv-ID\", \"quc-GT\", \"rw-RW\", \"ms-MY\", \"om-ET\", \"en-PH\", \"sn-ZW\", \"en-OZ\", \"su-ID\", \"sw-KE\", \"uz-UZ\", \"xh-ZA\", \"zu-ZA\"]}], \"metadata\": {\"head\": {\"unitsPerEm\": 1000, \"yMin\": -284, \"yMax\": 945}, \"hhea\": {\"ascender\": 976, \"descender\": -372, \"lineGap\": 0}, \"os2\": {\"sTypoAscender\": 976, \"sTypoDescender\": -372, \"sTypoLineGap\": 0, \"usWinAscent\": 976, \"usWinDescent\": 372, \"fsSelection\": 64}}, \"images\": [], \"replacedByRefs\": []}, \"index\": 0, \"files\": [{\"url\": \"https://font-public.canva.com/YAEe9XbWpNs/0/CinzelDecorative-Regular.b41865e5f86a443.144aee014e53ab5e3cfdd34eaa2023fa.ttf\", \"bucket\": \"font-public.canva.com\", \"key\": \"YAEe9XbWpNs/0/CinzelDecorative-Regular.b41865e5f86a443.144aee014e53ab5e3cfdd34eaa2023fa.ttf\", \"format\": \"OTF\", \"sizeBytes\": 58828}, {\"url\": \"https://font-public.canva.com/YAEe9XbWpNs/0/CinzelDecorative-Regular.b41865e5f86a443.5cd0abb0eceae34aa6f7e0a24e6a23ab.woff\", \"bucket\": \"font-public.canva.com\", \"key\": \"YAEe9XbWpNs/0/CinzelDecorative-Regular.b41865e5f86a443.5cd0abb0eceae34aa6f7e0a24e6a23ab.woff\", \"format\": \"WOFF\", \"sizeBytes\": 25924}, {\"url\": \"https://font-public.canva.com/YAEe9XbWpNs/0/CinzelDecorative-Regular.b41865e5f86a443.a845afc964b64d996f7a607942e459b5.woff2\", \"bucket\": \"font-public.canva.com\", \"key\": \"YAEe9XbWpNs/0/CinzelDecorative-Regular.b41865e5f86a443.a845afc964b64d996f7a607942e459b5.woff2\", \"format\": \"WOFF2\", \"sizeBytes\": 23392}]}, \"leading\": \"1400.0\", \"font-weight\": \"normal\", \"font-style\": \"normal\"}, \"index\": 1}, {\"text\": \"special menu\\n\", \"position\": [385.602090695631, 116.54608658515713, 53.025862603133945, 846.9078268296857], \"label\": \"pretitle\", \"style\": {\"text-transform\": \"uppercase\", \"color\": \"#e4ccb6\", \"list-level\": \"1.0\", \"font-size\": \"40.6153\", \"font-family\": \"YAFdtQi73Xs,0\", \"tracking\": \"496.0\", \"text-align\": \"center\", \"font-info\": {\"_id\": \"YAFdtQi73Xs\", \"fonts\": {\"style\": \"REGULAR\", \"styleName\": \"Regular\", \"postscriptName\": \"Montserrat-Regular\", \"weight\": 400, \"subsettedFiles\": [], \"metadata\": {\"head\": {\"unitsPerEm\": 1000, \"yMin\": -262, \"yMax\": 1043}, \"hhea\": {\"ascender\": 968, \"descender\": -251, \"lineGap\": 0}, \"os2\": {\"sTypoAscender\": 968, \"sTypoDescender\": -251, \"sTypoLineGap\": 0, \"usWinAscent\": 1109, \"usWinDescent\": 270, \"fsSelection\": 192}}, \"images\": [], \"replacedByRefs\": []}, \"index\": 0, \"files\": [{\"url\": \"https://font-public.canva.com/YAFdtQi73Xs/0/Montserrat-Regular.b1c97ca3ccb1538ad290d.b1c97ca3ccb1538ad290ddc7fb9e5999.ttf\", \"bucket\": \"font-public.canva.com\", \"key\": \"YAFdtQi73Xs/0/Montserrat-Regular.b1c97ca3ccb1538ad290d.b1c97ca3ccb1538ad290ddc7fb9e5999.ttf\", \"format\": \"OTF\", \"sizeBytes\": 263192}, {\"url\": \"https://font-public.canva.com/YAFdtQi73Xs/0/Montserrat-Regular.0a32c4953a7e6c3caf154.0a32c4953a7e6c3caf15493b72c6360c.woff\", \"bucket\": \"font-public.canva.com\", \"key\": \"YAFdtQi73Xs/0/Montserrat-Regular.0a32c4953a7e6c3caf154.0a32c4953a7e6c3caf15493b72c6360c.woff\", \"format\": \"WOFF\", \"sizeBytes\": 113984}, {\"url\": \"https://font-public.canva.com/YAFdtQi73Xs/0/Montserrat-Regular.b1c97ca3ccb1538ad290d.881b8da5ad9b82b143ab37dcdf069c4c.woff2\", \"bucket\": \"font-public.canva.com\", \"key\": \"YAFdtQi73Xs/0/Montserrat-Regular.b1c97ca3ccb1538ad290d.881b8da5ad9b82b143ab37dcdf069c4c.woff2\", \"format\": \"WOFF2\", \"sizeBytes\": 89932}]}, \"leading\": \"1400.0\"}, \"index\": 2}, {\"text\": \"This black pepper chicken is crispy, sticky, saucy, and sweet, which are ideal aspects of a wonderful chicken dish.\\n\", \"position\": [1289.8046321466925, 160.0976660097245, 125.57856527465457, 759.804667980551], \"label\": \"paragraph\", \"style\": {\"color\": \"#e3ccb5\", \"font-size\": \"26.6667\", \"font-family\": \"YAFdtQi73Xs,0\", \"text-align\": \"center\", \"font-info\": {\"_id\": \"YAFdtQi73Xs\", \"fonts\": {\"style\": \"REGULAR\", \"styleName\": \"Regular\", \"postscriptName\": \"Montserrat-Regular\", \"weight\": 400, \"subsettedFiles\": [], \"metadata\": {\"head\": {\"unitsPerEm\": 1000, \"yMin\": -262, \"yMax\": 1043}, \"hhea\": {\"ascender\": 968, \"descender\": -251, \"lineGap\": 0}, \"os2\": {\"sTypoAscender\": 968, \"sTypoDescender\": -251, \"sTypoLineGap\": 0, \"usWinAscent\": 1109, \"usWinDescent\": 270, \"fsSelection\": 192}}, \"images\": [], \"replacedByRefs\": []}, \"index\": 0, \"files\": [{\"url\": \"https://font-public.canva.com/YAFdtQi73Xs/0/Montserrat-Regular.b1c97ca3ccb1538ad290d.b1c97ca3ccb1538ad290ddc7fb9e5999.ttf\", \"bucket\": \"font-public.canva.com\", \"key\": \"YAFdtQi73Xs/0/Montserrat-Regular.b1c97ca3ccb1538ad290d.b1c97ca3ccb1538ad290ddc7fb9e5999.ttf\", \"format\": \"OTF\", \"sizeBytes\": 263192}, {\"url\": \"https://font-public.canva.com/YAFdtQi73Xs/0/Montserrat-Regular.0a32c4953a7e6c3caf154.0a32c4953a7e6c3caf15493b72c6360c.woff\", \"bucket\": \"font-public.canva.com\", \"key\": \"YAFdtQi73Xs/0/Montserrat-Regular.0a32c4953a7e6c3caf154.0a32c4953a7e6c3caf15493b72c6360c.woff\", \"format\": \"WOFF\", \"sizeBytes\": 113984}, {\"url\": \"https://font-public.canva.com/YAFdtQi73Xs/0/Montserrat-Regular.b1c97ca3ccb1538ad290d.881b8da5ad9b82b143ab37dcdf069c4c.woff2\", \"bucket\": \"font-public.canva.com\", \"key\": \"YAFdtQi73Xs/0/Montserrat-Regular.b1c97ca3ccb1538ad290d.881b8da5ad9b82b143ab37dcdf069c4c.woff2\", \"format\": \"WOFF2\", \"sizeBytes\": 89932}]}, \"text-transform\": \"none\", \"spacing\": \"0.0\", \"leading\": \"1400.0\", \"tracking\": \"0.0\"}, \"index\": 3}, {\"text\": \"See the Recipe\\n\", \"position\": [1499.533534190677, 344.7842970337123, 37.66164, 390.4314059325755], \"label\": \"paragraph\", \"style\": {\"text-transform\": \"uppercase\", \"color\": \"#e4ccb6\", \"font-size\": \"31.6918\", \"font-family\": \"YAFdJl36Ts4,0\", \"text-align\": \"center\", \"font-info\": {\"_id\": \"YAFdJl36Ts4\", \"fonts\": {\"style\": \"REGULAR\", \"styleName\": \"Normal\", \"postscriptName\": \"NeueEinstellung-Normal\", \"weight\": 400, \"subsettedFiles\": [], \"metadata\": {\"head\": {\"unitsPerEm\": 1000, \"yMin\": -309, \"yMax\": 1260}, \"hhea\": {\"ascender\": 1260, \"descender\": -329, \"lineGap\": 0}, \"os2\": {\"sTypoAscender\": 750, \"sTypoDescender\": -250, \"sTypoLineGap\": 0, \"usWinAscent\": 1260, \"usWinDescent\": 329, \"fsSelection\": 0}}, \"images\": [], \"replacedByRefs\": []}, \"index\": 0, \"files\": [{\"url\": \"https://font-public.canva.com/YAFdJl36Ts4/0/neueeinstellung-normal148489407663358956.9933e162f1121d7fd61bfa9fdea4d1d9.woff\", \"bucket\": \"font-public.canva.com\", \"key\": \"YAFdJl36Ts4/0/neueeinstellung-normal148489407663358956.9933e162f1121d7fd61bfa9fdea4d1d9.woff\", \"format\": \"WOFF\", \"sizeBytes\": 27304}, {\"url\": \"https://font-public.canva.com/YAFdJl36Ts4/0/neueeinstellung-normal119035956137818663.5705068d187669e651e6d6dbe4967e7b.otf\", \"bucket\": \"font-public.canva.com\", \"key\": \"YAFdJl36Ts4/0/neueeinstellung-normal119035956137818663.5705068d187669e651e6d6dbe4967e7b.otf\", \"format\": \"OTF_CFF\", \"sizeBytes\": 75732}, {\"url\": \"https://font-public.canva.com/YAFdJl36Ts4/0/neueeinstellung-normal119035956137818663.0a324e33cb87e4b80e5eba3b4c439099.woff2\", \"bucket\": \"font-public.canva.com\", \"key\": \"YAFdJl36Ts4/0/neueeinstellung-normal119035956137818663.0a324e33cb87e4b80e5eba3b4c439099.woff2\", \"format\": \"WOFF2\", \"sizeBytes\": 27116}, {\"url\": \"https://font-public.canva.com/YAFdJl36Ts4/0/quadratic-neueeinstellung-normal11903595.a4fbec920fb2b3d5570e31792770368e.woff\", \"bucket\": \"font-public.canva.com\", \"key\": \"YAFdJl36Ts4/0/quadratic-neueeinstellung-normal11903595.a4fbec920fb2b3d5570e31792770368e.woff\", \"format\": \"WOFF\", \"sizeBytes\": 27952}]}, \"spacing\": \"0.0\", \"leading\": \"1400.0\", \"tracking\": \"0.0\"}, \"index\": 4}, {\"text\": \"Suhoor\\n\", \"position\": [444.98575803505025, 54.97848182443016, 211.22571579083632, 970.0430363511396], \"label\": \"title\", \"style\": {\"color\": \"#d49926\", \"font-size\": \"148.148\", \"font-family\": \"YAEe9XbWpNs,0\", \"tracking\": \"89.0\", \"text-align\": \"center\", \"font-info\": {\"_id\": \"YAEe9XbWpNs\", \"fonts\": {\"style\": \"REGULAR\", \"styleName\": \"Regular\", \"postscriptName\": \"CinzelDecorative-Regular\", \"weight\": 400, \"subsettedFiles\": [{\"type\": \"LOCALE_SUBSETTED_FONT_FILE\", \"url\": \"https://font-public.canva.com/YAEe9XbWpNs/0/subsets/CinzelDecorative-Regular.b41865e5f86a443.727c19e53000d2c4c27f062b210d0e47.ttf\", \"format\": \"OTF\", \"sizeBytes\": 50928, \"unicodeRanges\": [{\"start\": \"0000\", \"end\": \"007F\"}, {\"start\": \"0080\", \"end\": \"00FF\"}, {\"start\": \"0100\", \"end\": \"017F\"}, {\"start\": \"1E00\", \"end\": \"1EFF\"}], \"supportedLocales\": [\"en-AU\", \"en-instrume\", \"en-psaccent\", \"en\", \"en-GB\", \"en-IN\", \"jv-ID\", \"quc-GT\", \"rw-RW\", \"ms-MY\", \"om-ET\", \"en-PH\", \"sn-ZW\", \"en-OZ\", \"su-ID\", \"sw-KE\", \"uz-UZ\", \"xh-ZA\", \"zu-ZA\"]}, {\"type\": \"LOCALE_SUBSETTED_FONT_FILE\", \"url\": \"https://font-public.canva.com/YAEe9XbWpNs/0/subsets/CinzelDecorative-Regular.b41865e5f86a443.018333806f9baa45e457caeeffbce25.woff2\", \"format\": \"WOFF2\", \"sizeBytes\": 19616, \"unicodeRanges\": [{\"start\": \"0000\", \"end\": \"007F\"}, {\"start\": \"0080\", \"end\": \"00FF\"}, {\"start\": \"0100\", \"end\": \"017F\"}, {\"start\": \"1E00\", \"end\": \"1EFF\"}], \"supportedLocales\": [\"en-AU\", \"en-instrume\", \"en-psaccent\", \"en\", \"en-GB\", \"en-IN\", \"jv-ID\", \"quc-GT\", \"rw-RW\", \"ms-MY\", \"om-ET\", \"en-PH\", \"sn-ZW\", \"en-OZ\", \"su-ID\", \"sw-KE\", \"uz-UZ\", \"xh-ZA\", \"zu-ZA\"]}, {\"type\": \"LOCALE_SUBSETTED_FONT_FILE\", \"url\": \"https://font-public.canva.com/YAEe9XbWpNs/0/subsets/CinzelDecorative-Regular.b41865e5f86a443.98e3da708d9186b7ea1e9110280ab1c4.woff\", \"format\": \"WOFF\", \"sizeBytes\": 21556, \"unicodeRanges\": [{\"start\": \"0000\", \"end\": \"007F\"}, {\"start\": \"0080\", \"end\": \"00FF\"}, {\"start\": \"0100\", \"end\": \"017F\"}, {\"start\": \"1E00\", \"end\": \"1EFF\"}], \"supportedLocales\": [\"en-AU\", \"en-instrume\", \"en-psaccent\", \"en\", \"en-GB\", \"en-IN\", \"jv-ID\", \"quc-GT\", \"rw-RW\", \"ms-MY\", \"om-ET\", \"en-PH\", \"sn-ZW\", \"en-OZ\", \"su-ID\", \"sw-KE\", \"uz-UZ\", \"xh-ZA\", \"zu-ZA\"]}], \"metadata\": {\"head\": {\"unitsPerEm\": 1000, \"yMin\": -284, \"yMax\": 945}, \"hhea\": {\"ascender\": 976, \"descender\": -372, \"lineGap\": 0}, \"os2\": {\"sTypoAscender\": 976, \"sTypoDescender\": -372, \"sTypoLineGap\": 0, \"usWinAscent\": 976, \"usWinDescent\": 372, \"fsSelection\": 64}}, \"images\": [], \"replacedByRefs\": []}, \"index\": 0, \"files\": [{\"url\": \"https://font-public.canva.com/YAEe9XbWpNs/0/CinzelDecorative-Regular.b41865e5f86a443.144aee014e53ab5e3cfdd34eaa2023fa.ttf\", \"bucket\": \"font-public.canva.com\", \"key\": \"YAEe9XbWpNs/0/CinzelDecorative-Regular.b41865e5f86a443.144aee014e53ab5e3cfdd34eaa2023fa.ttf\", \"format\": \"OTF\", \"sizeBytes\": 58828}, {\"url\": \"https://font-public.canva.com/YAEe9XbWpNs/0/CinzelDecorative-Regular.b41865e5f86a443.5cd0abb0eceae34aa6f7e0a24e6a23ab.woff\", \"bucket\": \"font-public.canva.com\", \"key\": \"YAEe9XbWpNs/0/CinzelDecorative-Regular.b41865e5f86a443.5cd0abb0eceae34aa6f7e0a24e6a23ab.woff\", \"format\": \"WOFF\", \"sizeBytes\": 25924}, {\"url\": \"https://font-public.canva.com/YAEe9XbWpNs/0/CinzelDecorative-Regular.b41865e5f86a443.a845afc964b64d996f7a607942e459b5.woff2\", \"bucket\": \"font-public.canva.com\", \"key\": \"YAEe9XbWpNs/0/CinzelDecorative-Regular.b41865e5f86a443.a845afc964b64d996f7a607942e459b5.woff2\", \"format\": \"WOFF2\", \"sizeBytes\": 23392}]}, \"leading\": \"1400.0\", \"font-weight\": \"normal\", \"font-style\": \"normal\"}, \"index\": 6}]"}