{"id": "EAEwdDlMyCE-1-0-web-2-EKKE92zRPj8", "caption": "The image is an advertisement for the December issue of a magazine, featuring a pink archway. The advertisement is promoting a \"Hot Offer\" and encourages viewers to \"Can't wait the moment.\" The text is displayed in a large, bold font, with the words \"December Issue\" and \"Hot Offer\" positioned above the pink archway, and \"Can't wait the moment\" below it.", "original_title": "December Issue Promotion Instagram Post", "tags": ["blue", "white", "minimalist", "sale", "offer", "discount", "design", "december", "illustration", "background", "season", "vector", "winter", "promotion", "price", "business", "store", "decoration", "promo"], "texts": ["December\nIssue", "Hot \noffer", "CAnt wait the moment"], "category": "Instagram Posts", "text_layer_info": "[{\"text\": \"\\nCAnt wait the moment\\n\", \"position\": [889.7595434966829, 108.0, 104.808965, 716.6533176880279], \"label\": \"subtitle\", \"style\": {\"leading\": \"1150.0\", \"list-level\": \"1.0\", \"font-size\": \"44.6168\", \"font-family\": \"YAD0s3O1iG4,1\", \"text-transform\": \"none\", \"color\": \"#000000\", \"font-weight\": \"normal\", \"font-style\": \"normal\", \"tracking\": \"0.0\"}, \"index\": 0}, {\"text\": \"Hot \\noffer\\n\", \"position\": [71.07683177430499, 673.4660363349042, 104.84065185490137, 298.5339636650958], \"label\": \"pretitle\", \"style\": {\"leading\": \"1150.0\", \"list-level\": \"1.0\", \"font-size\": \"58.6667\", \"font-family\": \"YAD0s3O1iG4,1\", \"text-align\": \"end\", \"text-transform\": \"none\", \"color\": \"#000000\", \"font-weight\": \"normal\", \"font-style\": \"normal\", \"tracking\": \"0.0\"}, \"index\": 1}, {\"text\": \"December\\nIssue\\n\", \"position\": [398.52274199999994, 121.35515602163532, 282.954516, 837.2896879567294], \"label\": \"title\", \"style\": {\"leading\": \"910.0\", \"font-size\": \"134.1106\", \"font-family\": \"YALBs4GWnJw,0\", \"tracking\": \"-34.0\", \"text-align\": \"center\", \"font-info\": {\"_id\": \"YALBs4GWnJw\", \"fonts\": {\"style\": \"REGULAR\", \"styleName\": \"Regular\", \"postscriptName\": \"YesevaOne-Regular\", \"weight\": 400, \"subsettedFiles\": [{\"type\": \"LOCALE_SUBSETTED_FONT_FILE\", \"url\": \"https://font-public.canva.com/YALBs4GWnJw/0/subsets/YesevaOne-Regular.9d02ace9ae7f5aa7e5b143.02cd8f4b15a5b4a2f4f8f83ca15475b.woff2\", \"format\": \"WOFF2\", \"sizeBytes\": 19856, \"unicodeRanges\": [{\"start\": \"0000\", \"end\": \"007F\"}, {\"start\": \"0080\", \"end\": \"00FF\"}, {\"start\": \"0100\", \"end\": \"017F\"}, {\"start\": \"1E00\", \"end\": \"1EFF\"}], \"supportedLocales\": [\"en-AU\", \"en-instrume\", \"en-psaccent\", \"en\", \"en-GB\", \"en-IN\", \"jv-ID\", \"quc-GT\", \"rw-RW\", \"ms-MY\", \"om-ET\", \"en-PH\", \"sn-ZW\", \"en-OZ\", \"su-ID\", \"sw-KE\", \"uz-UZ\", \"xh-ZA\", \"zu-ZA\"]}, {\"type\": \"LOCALE_SUBSETTED_FONT_FILE\", \"url\": \"https://font-public.canva.com/YALBs4GWnJw/0/subsets/YesevaOne-Regular.9d02ace9ae7f5aa7e5b143.3da797c8c2263174dfee2af1edc4ba85.woff\", \"format\": \"WOFF\", \"sizeBytes\": 25624, \"unicodeRanges\": [{\"start\": \"0000\", \"end\": \"007F\"}, {\"start\": \"0080\", \"end\": \"00FF\"}, {\"start\": \"0100\", \"end\": \"017F\"}, {\"start\": \"1E00\", \"end\": \"1EFF\"}], \"supportedLocales\": [\"en-AU\", \"en-instrume\", \"en-psaccent\", \"en\", \"en-GB\", \"en-IN\", \"jv-ID\", \"quc-GT\", \"rw-RW\", \"ms-MY\", \"om-ET\", \"en-PH\", \"sn-ZW\", \"en-OZ\", \"su-ID\", \"sw-KE\", \"uz-UZ\", \"xh-ZA\", \"zu-ZA\"]}, {\"type\": \"LOCALE_SUBSETTED_FONT_FILE\", \"url\": \"https://font-public.canva.com/YALBs4GWnJw/0/subsets/YesevaOne-Regular.9d02ace9ae7f5aa7e5b143.06756100d4584d088a6fb0850e837625.ttf\", \"format\": \"OTF\", \"sizeBytes\": 52992, \"unicodeRanges\": [{\"start\": \"0000\", \"end\": \"007F\"}, {\"start\": \"0080\", \"end\": \"00FF\"}, {\"start\": \"0100\", \"end\": \"017F\"}, {\"start\": \"1E00\", \"end\": \"1EFF\"}], \"supportedLocales\": [\"en-AU\", \"en-instrume\", \"en-psaccent\", \"en\", \"en-GB\", \"en-IN\", \"jv-ID\", \"quc-GT\", \"rw-RW\", \"ms-MY\", \"om-ET\", \"en-PH\", \"sn-ZW\", \"en-OZ\", \"su-ID\", \"sw-KE\", \"uz-UZ\", \"xh-ZA\", \"zu-ZA\"]}], \"metadata\": {\"head\": {\"unitsPerEm\": 1000, \"yMin\": -310, \"yMax\": 1079}, \"hhea\": {\"ascender\": 915, \"descender\": -240, \"lineGap\": 0}, \"os2\": {\"sTypoAscender\": 915, \"sTypoDescender\": -240, \"sTypoLineGap\": 0, \"usWinAscent\": 1079, \"usWinDescent\": 310, \"fsSelection\": 192}}, \"images\": [], \"replacedByRefs\": []}, \"index\": 0, \"files\": [{\"url\": \"https://font-public.canva.com/YALBs4GWnJw/0/YesevaOne-Regular.ttf\", \"bucket\": \"font-public.canva.com\", \"key\": \"YALBs4GWnJw/0/YesevaOne-Regular.ttf\", \"format\": \"OTF\", \"sizeBytes\": 108016}, {\"url\": \"https://font-public.canva.com/YALBs4GWnJw/0/YesevaOne-Regular.woff\", \"bucket\": \"font-public.canva.com\", \"key\": \"YALBs4GWnJw/0/YesevaOne-Regular.woff\", \"format\": \"WOFF\", \"sizeBytes\": 46612}, {\"url\": \"https://font-public.canva.com/YALBs4GWnJw/0/YesevaOne-Regular.9d02ace9ae7f5aa7e5b143.8d9d0b677d9353955f3ba5469db1b8ca.woff2\", \"bucket\": \"font-public.canva.com\", \"key\": \"YALBs4GWnJw/0/YesevaOne-Regular.9d02ace9ae7f5aa7e5b143.8d9d0b677d9353955f3ba5469db1b8ca.woff2\", \"format\": \"WOFF2\", \"sizeBytes\": 41504}]}, \"color\": \"#000000\", \"font-weight\": \"normal\", \"font-style\": \"normal\"}, \"index\": 3}]"}